{
    "resources":[
                 {
                 "title":"Ulta at a Glance",
                 "shortDescription":"This is a short description.",
                 "source":"Ulta Beauty",
                 "link":"ulta_at_a_glance",
                 "imageURL":"document",
                 "type" : 1
                 },
                 {
                 "title":"Work for Ulta Beauty",
                 "shortDescription":"This is a short description.",
                 "source":"Apple, Inc.",
                 "link":"ulta_recrutiing",
                 "imageURL":"document",
                 "type" : 1
                 },
                 {
                 "title":"Ulta App",
                 "shortDescription":"This is a short description.",
                 "source":"Apple, Inc.",
                 "link":"https://www.ulta.com/app/",
                 "imageURL":"website",
                 "type" : 2
                 },
                 {
                 "title":"ECC Source Code",
                 "shortDescription":"The source code for the ECC code app we built for this event. Feel free to explore!",
                 "source":"GitHub, Inc",
                 "link":"https://github.com/ultabeauty/ECC",
                 "imageURL":"code",
                 "type" : 2
                 },
                 {
                 "title":"Swift Playgrounds",
                 "shortDescription":"Swift Playgrounds is a revolutionary app for iPad that makes it fun to learn and experiment with code.",
                 "source":"Apple, Inc.",
                 "link":"https://www.google.com",
                 "imageURL":"code",
                 "type" : 0
                 },
                 {
                 "title":"Intro to App Development with Swift",
                 "shortDescription":"This course is designed to help you build a solid foundation in programming fundamentals using Swift as the language.",
                 "source":"Apple, Inc.",
                 "link":"https://itunes.apple.com/WebObjects/MZStore.woa/wa/viewBook?id=1118575552&mt=11&v0=www-ae-education-everyone-can-code-book-app-development-swift-preview",
                 "imageURL":"code",
                 "type" : 0
                 },
                 {
                 "title":"Learn to Code 1 & 2",
                 "shortDescription":"This Teacher Guide is designed to help you bring Swift Playgrounds.",
                 "source":"Apple, Inc.",
                 "link":"https://www.google.com",
                 "imageURL":"code",
                 "type" : 0
                 },
                 {
                 "title":"App Development with Swift",
                 "shortDescription":"This course is designed to teach you the skills needed to be an app developer capable of bringing your own ideas to life. Whether you’re new to coding or want to expand your skills, by the end of this course you should be able to build a fully functioning app of your own design.",
                 "source":"Apple, Inc.",
                 "link":"https://itunes.apple.com/book/id1219117996",
                 "imageURL":"code",
                 "type" : 0
                 },
                 {
                 "title":"Swift",
                 "shortDescription":"This is a short description.",
                 "source":"Apple, Inc.",
                 "link":"https://www.google.com",
                 "imageURL":"code",
                 "type" : 0
                 }
                 ]
}
